Multi_Tenant-0.6.dist-info/DESCRIPTION.rst
Multi_Tenant-0.6.dist-info/entry_points.txt
Multi_Tenant-0.6.dist-info/METADATA
Multi_Tenant-0.6.dist-info/metadata.json
Multi_Tenant-0.6.dist-info/pbr.json
Multi_Tenant-0.6.dist-info/RECORD
Multi_Tenant-0.6.dist-info/top_level.txt
Multi_Tenant-0.6.dist-info/WHEEL
multicloudclient/__init__.py
multicloudclient/command.py
multicloudclient/commandshell.py
multicloudclient/createtenants.py
multicloudclient/multitenantservice.py
multicloudclient/quotasservice.py
multicloudclient/quotasupdate.py
