Metadata-Version: 2.0
Name: Multi-Tenant
Version: 0.6
Summary: Multi-cloud API
Home-page: https://gecgithub01.walmart.com/rnagpal/python-multicloudclient.git
Author: UNKNOWN
Author-email: UNKNOWN
License: UNKNOWN
Platform: Any
Classifier: Development Status :: 3 - Alpha
Classifier: License :: OSI Approved :: Apache Software License
Classifier: Programming Language :: Python
Classifier: Programming Language :: Python :: 2
Classifier: Programming Language :: Python :: 2.7
Classifier: Programming Language :: Python :: 3
Classifier: Programming Language :: Python :: 3.2
Classifier: Intended Audience :: Developers
Classifier: Environment :: Console
